[
    {
        "categories": "Nusantara",
        "title": "Lima Kecamatan di Sukabumi Laporkan Kerusakan Akibat Gempa",
        "scrapped_time": "Mar 10 2020 22:11:43",
        "published_time": "Selasa 10 Mar 2020 22:11"
    },
    {
        "categories": "Sepak Bola",
        "title": "Produktivitas Gol Merosot, Ada Apa dengan Griezmann? ",
        "scrapped_time": "Mar 10 2020 22:11:43",
        "published_time": "Selasa 10 Mar 2020 22:09"
    },
    {
        "categories": "Nusantara",
        "title": "Isak Tangis Sambut Jenazah TNI Korban Penembakan KKB ",
        "scrapped_time": "Mar 10 2020 22:11:44",
        "published_time": "Selasa 10 Mar 2020 22:08"
    },
    {
        "categories": "Nusantara",
        "title": "DBD di Sleman Tertinggi di Daerah Padat Penduduk",
        "scrapped_time": "Mar 10 2020 22:11:44",
        "published_time": "Selasa 10 Mar 2020 22:06"
    },
    {
        "categories": "Khazanah",
        "title": "Hakim bin Hizam Kaya dan Dermawan Berkat Doa Rasulullah SAW",
        "scrapped_time": "Mar 10 2020 22:11:44",
        "published_time": "Selasa 10 Mar 2020 22:05"
    },
    {
        "categories": "Nusantara",
        "title": "Skateboard Indonesia Diharap Dapat Perhatian Lebih",
        "scrapped_time": "Mar 10 2020 22:11:45",
        "published_time": "Selasa 10 Mar 2020 22:04"
    },
    {
        "categories": "Sepak Bola",
        "title": "Gregoria Ingin Tampil Lepas di All England 2020",
        "scrapped_time": "Mar 10 2020 22:11:45",
        "published_time": "Selasa 10 Mar 2020 22:00"
    },
    {
        "categories": "Senggang",
        "title": "Rekaman di Abbey Road, Govinda Taklukan Cuaca Dingin",
        "scrapped_time": "Mar 10 2020 22:11:46",
        "published_time": "Selasa 10 Mar 2020 21:52"
    },
    {
        "categories": "Nusantara",
        "title": "Jateng Minta Tambahan Puluhan Ribu APD ke Pemerintah Pusat",
        "scrapped_time": "Mar 10 2020 22:11:46",
        "published_time": "Selasa 10 Mar 2020 21:50"
    },
    {
        "categories": "Sepak Bola",
        "title": "Peselancar Indonesia ke El Savador Incar Tiket Olimpiade",
        "scrapped_time": "Mar 10 2020 22:11:46",
        "published_time": "Selasa 10 Mar 2020 21:47"
    },
    {
        "categories": "Khazanah",
        "title": "Ini Dia Satu-Satunya Sahabat Rasulullah yang Lahir di Kabah ",
        "scrapped_time": "Mar 10 2020 22:11:46",
        "published_time": "Selasa 10 Mar 2020 21:44"
    },
    {
        "categories": "Otomotif",
        "title": "Porsche Borong Nominasi di World Performance Car 2020",
        "scrapped_time": "Mar 10 2020 22:11:47",
        "published_time": "Selasa 10 Mar 2020 21:43"
    },
    {
        "categories": "Ekonomi",
        "title": "Corona Porak Porandakan Rantai Pasokan Elektronik Dunia ",
        "scrapped_time": "Mar 10 2020 22:11:47",
        "published_time": "Selasa 10 Mar 2020 21:40"
    },
    {
        "categories": "Gaya Hidup",
        "title": "Akibat Terlalu Lama Menatap Layar Gadget",
        "scrapped_time": "Mar 10 2020 22:11:47",
        "published_time": "Selasa 10 Mar 2020 21:39"
    },
    {
        "categories": "IHRAM.CO.ID",
        "title": "Kemenag akan Tutup Sementara Aplikasi Pendaftaran Umroh",
        "scrapped_time": "Mar 10 2020 22:11:48",
        "published_time": "Selasa 10 Mar 2020 21:39"
    },
    {
        "categories": "Nusantara",
        "title": "Ombudsman Dorong Mediasi Petambak Udang Pesisir Barat",
        "scrapped_time": "Mar 10 2020 22:11:48",
        "published_time": "Selasa 10 Mar 2020 21:38"
    },
    {
        "categories": "Nusantara",
        "title": "Legislator Minta Mendagri Panggil Bupati Nduga",
        "scrapped_time": "Mar 10 2020 22:11:48",
        "published_time": "Selasa 10 Mar 2020 21:36"
    },
    {
        "categories": "Nusantara",
        "title": "Empat Pasien RSUD Singkawang Negatif Covid-19",
        "scrapped_time": "Mar 10 2020 22:11:49",
        "published_time": "Selasa 10 Mar 2020 21:35"
    },
    {
        "categories": "Sepak Bola",
        "title": "Persiapan Panjat Tebing Jelang Olimpiade Terkendala Corona",
        "scrapped_time": "Mar 10 2020 22:11:49",
        "published_time": "Selasa 10 Mar 2020 21:33"
    },
    {
        "categories": "Ekonomi",
        "title": "Pemerintah Diminta Tertibkan Aturan Tata Kelola Pelabuhan",
        "scrapped_time": "Mar 10 2020 22:11:49",
        "published_time": "Selasa 10 Mar 2020 21:32"
    },
    {
        "categories": "Khazanah",
        "title": "Melihat Makam Penyebar Islam di Nusantara (2)",
        "scrapped_time": "Mar 10 2020 22:11:50",
        "published_time": "Selasa 10 Mar 2020 21:28"
    },
    {
        "categories": "Khazanah",
        "title": "Melihat Makam Penyebar Islam di Nusantara (1)",
        "scrapped_time": "Mar 10 2020 22:11:50",
        "published_time": "Selasa 10 Mar 2020 21:28"
    },
    {
        "categories": "Nusantara",
        "title": "Dua Penipu Modus Tukar Kartu ATM adalah Residivis",
        "scrapped_time": "Mar 10 2020 22:11:50",
        "published_time": "Selasa 10 Mar 2020 21:27"
    },
    {
        "categories": "Nusantara",
        "title": "Operasi Cempaka Krakatau 2020 Amankan 41 Tersangka",
        "scrapped_time": "Mar 10 2020 22:11:51",
        "published_time": "Selasa 10 Mar 2020 21:26"
    },
    {
        "categories": "Pendidikan",
        "title": "UNJ akan Bahas Peran Sultan Zainal Abidin Syah untuk NKRI ",
        "scrapped_time": "Mar 10 2020 22:11:51",
        "published_time": "Selasa 10 Mar 2020 21:26"
    }
]